mblm/__init__.py
mblm/py.typed
mblm/data/__init__.py
mblm/data/datasets.py
mblm/data/types.py
mblm/data/dataset/beep.py
mblm/data/dataset/clevr.py
mblm/data/dataset/pg19.py
mblm/data/dataset/pg19_masked.py
mblm/data/utils/__init__.py
mblm/data/utils/bytes.py
mblm/data/utils/image.py
mblm/data/utils/misc.py
mblm/data/utils/tokenizer.py
mblm/model/block.py
mblm/model/config.py
mblm/model/embeddings.py
mblm/model/mamba.py
mblm/model/mamba_shim.py
mblm/model/mblm.py
mblm/model/transformer.py
mblm/model/utils.py
mblm/train/mblm.py
mblm/train/core/__init__.py
mblm/train/core/config.py
mblm/train/core/iter.py
mblm/train/core/trainer.py
mblm/utils/__init__.py
mblm/utils/cuda.py
mblm/utils/distributed.py
mblm/utils/io.py
mblm/utils/logging.py
mblm/utils/misc.py
mblm/utils/seed.py
mblm/utils/stream.py
mblm/utils/top_n.py
mblm-0.4.0.dist-info/METADATA
mblm-0.4.0.dist-info/WHEEL
mblm-0.4.0.dist-info/licenses/LICENSE
mblm-0.4.0.dist-info/RECORD
