Metadata-Version: 2.4
Name: mblm
Version: 0.4.0
Summary: Multiscale Byte Language Model
Project-URL: homepage, https://github.com/ai4sd/mblm
Project-URL: source, https://github.com/ai4sd/mblm
Project-URL: releasenotes, https://github.com/ai4sd/mblm/releases
Author-email: Eric Egli <eric.christian.egli@ibm.com>, Jannis Born <jab@zurich.ibm.com>
License-File: LICENSE
Keywords: Byte Language Models,Hierarchical Architectures,Language Models,Long Context Window,Machine Learning
Classifier: Development Status :: 4 - Beta
Classifier: Intended Audience :: Developers
Classifier: Intended Audience :: Science/Research
Classifier: License :: OSI Approved :: MIT License
Classifier: Programming Language :: Python :: 3
Classifier: Programming Language :: Python :: 3.10
Classifier: Programming Language :: Python :: 3.11
Classifier: Programming Language :: Python :: 3.12
Classifier: Programming Language :: Python :: 3.13
Classifier: Topic :: Scientific/Engineering :: Artificial Intelligence
Classifier: Typing :: Typed
Requires-Python: >=3.10
Requires-Dist: einops>=0.8.0
Requires-Dist: filelock>=3.16.1
Requires-Dist: mambapy>=1.2.0
Requires-Dist: megabyte-pytorch>=0.3.6
Requires-Dist: numpy>=2.1.1
Requires-Dist: pillow>=11.0.0
Requires-Dist: pydantic>=2.9.2
Requires-Dist: pyyaml>=6.0.2
Requires-Dist: tqdm>=4.66.5
